hashcrack_jtr/__init__.py
hashcrack_jtr/config.py
hashcrack_jtr/john.py
hashcrack_jtr/version.py
hashcrack_jtr/static/john.tar.xz
hashcrack_jtr-23.2.19.dist-info/METADATA
hashcrack_jtr-23.2.19.dist-info/WHEEL
hashcrack_jtr-23.2.19.dist-info/entry_points.txt
hashcrack_jtr-23.2.19.dist-info/top_level.txt
hashcrack_jtr-23.2.19.dist-info/RECORD
