Metadata-Version: 2.1
Name: hashcrack-jtr
Version: 23.2.19
Summary: CLI install of John-the-Ripper for hashcrack.
Home-page: https://github.com/bannsec/hashcrack-jtr
Author: Michael Bann
Author-email: self@bannsecurity.com
License: MIT
Keywords: password cracking john jtr
Platform: UNKNOWN
Classifier: Development Status :: 3 - Alpha
Classifier: Intended Audience :: End Users/Desktop
Classifier: License :: OSI Approved :: GNU General Public License v2 or later (GPLv2+)
Classifier: Programming Language :: Python :: 3
Classifier: Operating System :: POSIX :: Linux
Classifier: Environment :: Console
Requires-Dist: prettytable
Requires-Dist: appdirs
Requires-Dist: prompt-toolkit
Provides-Extra: dev
Requires-Dist: ipython ; extra == 'dev'
Requires-Dist: twine ; extra == 'dev'
Requires-Dist: pytest ; extra == 'dev'
Requires-Dist: python-coveralls ; extra == 'dev'
Requires-Dist: coverage (==4.5.4) ; extra == 'dev'
Requires-Dist: pytest-cov ; extra == 'dev'
Requires-Dist: pytest-xdist ; extra == 'dev'
Requires-Dist: sphinxcontrib-napoleon ; extra == 'dev'
Requires-Dist: sphinx-rtd-theme ; extra == 'dev'
Requires-Dist: sphinx-autodoc-typehints ; extra == 'dev'
Requires-Dist: restview ; extra == 'dev'
